cartils/__init__.py
cartils/encoding.py
cartils/enums.py
cartils/external.py
cartils/generators.py
cartils/graphics.py
cartils/helpers.py
cartils/logger.py
cartils-0.1.2.dist-info/METADATA
cartils-0.1.2.dist-info/WHEEL
cartils-0.1.2.dist-info/top_level.txt
cartils-0.1.2.dist-info/RECORD
