Metadata-Version: 2.1
Name: cartils
Version: 0.1.2
Summary: A collection of useful Python utilities
Home-page: https://github.com/jfcarter2358/cartils
Author: John Carter
Author-email: jfcarter2358@gmail.com
License: UNKNOWN
Platform: UNKNOWN
Requires-Python: >=3.7
Requires-Dist: colorama (==0.4.4)
Requires-Dist: cursor (==1.3.4)
